remot3/__init__.py
remot3/remot3.py
remot3-0.1.0.dist-info/LICENSE
remot3-0.1.0.dist-info/METADATA
remot3-0.1.0.dist-info/WHEEL
remot3-0.1.0.dist-info/top_level.txt
remot3-0.1.0.dist-info/RECORD
