Metadata-Version: 2.1
Name: remot3
Version: 0.1.0
Summary: Implementation of the remot3.it API
Home-page: https://github.com/twaclaw/remot3
Author: Diego Sandoval
Author-email: dsandovalv@gmail.com
License: MIT license
Keywords: remot3
Platform: UNKNOWN
Classifier: Development Status :: 2 - Pre-Alpha
Classifier: Intended Audience :: Developers
Classifier: License :: OSI Approved :: MIT License
Classifier: Natural Language :: English
Classifier: Programming Language :: Python :: 2
Classifier: Programming Language :: Python :: 2.7
Classifier: Programming Language :: Python :: 3
Classifier: Programming Language :: Python :: 3.4
Classifier: Programming Language :: Python :: 3.5
Classifier: Programming Language :: Python :: 3.6
Classifier: Programming Language :: Python :: 3.7
Requires-Dist: requests
